team4159_hoard-0.0.1.dist-info/RECORD
team4159_hoard-0.0.1.dist-info/metadata.json
team4159_hoard-0.0.1.dist-info/WHEEL
team4159_hoard-0.0.1.dist-info/DESCRIPTION.rst
team4159_hoard-0.0.1.dist-info/top_level.txt
team4159_hoard-0.0.1.dist-info/METADATA
hoard/__init__.py
